{"list":[{"id":"54","type":"relationship","label":"Works","start":{"id":"53","labels":["Person","Teacher"]},"end":{"id":"42","labels":["Kafedra"]}},{"id":"56","type":"relationship","label":"Works","start":{"id":"54","labels":["Person","Teacher"]},"end":{"id":"42","labels":["Kafedra"]}},{"id":"57","type":"relationship","label":"Works","start":{"id":"55","labels":["Person","Teacher"]},"end":{"id":"43","labels":["Kafedra"]}},{"id":"58","type":"relationship","label":"Works","start":{"id":"56","labels":["Person","Teacher"]},"end":{"id":"44","labels":["Kafedra"]}},{"id":"59","type":"relationship","label":"Works","start":{"id":"57","labels":["Person","Teacher"]},"end":{"id":"43","labels":["Kafedra"]}},{"id":"60","type":"relationship","label":"Works","start":{"id":"58","labels":["Person","Teacher"]},"end":{"id":"43","labels":["Kafedra"]}},{"id":"61","type":"relationship","label":"Works","start":{"id":"59","labels":["Person","Teacher"]},"end":{"id":"43","labels":["Kafedra"]}},{"id":"62","type":"relationship","label":"Works","start":{"id":"60","labels":["Person","Teacher"]},"end":{"id":"43","labels":["Kafedra"]}}]}